vidqa/__init__.py
vidqa/check_path.py
vidqa/cli.py
vidqa/config.ini
vidqa/config.py
vidqa/ffprobe_micro.py
vidqa/make_reencode.py
vidqa/utils.py
vidqa/video_report.py
vidqa/video_tools.py
vidqa/vidqa.py
vidqa-0.1.19.dist-info/AUTHORS.rst
vidqa-0.1.19.dist-info/LICENSE
vidqa-0.1.19.dist-info/METADATA
vidqa-0.1.19.dist-info/WHEEL
vidqa-0.1.19.dist-info/entry_points.txt
vidqa-0.1.19.dist-info/top_level.txt
vidqa-0.1.19.dist-info/RECORD
