Metadata-Version: 2.1
Name: vidqa
Version: 0.1.19
Summary: Quality assurance for audiovisual collections
Home-page: https://github.com/apenasrr/vidqa
Author: apenasrr
Author-email: apenasrr@gmail.com
License: MIT license
Keywords: vidqa
Classifier: Development Status :: 2 - Pre-Alpha
Classifier: Intended Audience :: Developers
Classifier: License :: OSI Approved :: MIT License
Classifier: Natural Language :: English
Classifier: Programming Language :: Python :: 3
Classifier: Programming Language :: Python :: 3.6
Classifier: Programming Language :: Python :: 3.7
Classifier: Programming Language :: Python :: 3.8
Requires-Python: >=3.6
License-File: LICENSE
License-File: AUTHORS.rst
Requires-Dist: Click >=7.0
Requires-Dist: natsort >=8.2.0
Requires-Dist: Unidecode >=1.3.4
Requires-Dist: pandas
